BetterJsonFS/JsonFS.py
BetterJsonFS/__init__.py
JsonFS/JsonFS.py
JsonFS/__init__.py
betterjsonfs-0.1.3.dist-info/LICENSE
betterjsonfs-0.1.3.dist-info/METADATA
betterjsonfs-0.1.3.dist-info/WHEEL
betterjsonfs-0.1.3.dist-info/top_level.txt
betterjsonfs-0.1.3.dist-info/RECORD
