Metadata-Version: 2.1
Name: betterjsonfs
Version: 0.1.3
Summary: A horrible Idea
Home-page: https://bit.ly/betterjsonfs
Author: Kool Author
Author-email: besimat444@sofiarae.com
License: UNKNOWN
Platform: UNKNOWN
Classifier: Programming Language :: Python :: 3
Classifier: License :: OSI Approved :: MIT License
Classifier: Operating System :: OS Independent
Requires-Python: >=3.6
